[
    {"nombre": "Iphone 15 128GB", "detail": "", "categoria": "iphone", "precio": 1020, "pic": "../assets/img/iphone15.png", "text": "https://wa.me/1156634529?text=Hola!%20Me%20interesa%20un%20producto de su página,%20quisiera%20tener%20mas%20información."},
    {"nombre": "Iphone 15 Pro 128GB", "detail": "", "categoria": "iphone", "precio": 1350, "pic": "../assets/img/iphone15_pro.png", "text": "https://wa.me/1156634529?text=Hola!%20Me%20interesa%20un%20producto de su página,%20quisiera%20tener%20mas%20información."},
    {"nombre": "Iphone 15 Pro 256GB", "detail": "", "categoria": "iphone", "precio": 1450, "pic": "../assets/img/iphone15_pro.png", "text": "https://wa.me/1156634529?text=Hola!%20Me%20interesa%20un%20producto de su página,%20quisiera%20tener%20mas%20información."},
    {"nombre": "Iphone 15 Pro Max 256GB", "detail": "", "categoria": "iphone", "precio": 1690, "pic": "../assets/img/iphone15_pro_max.png", "text": "https://wa.me/1156634529?text=Hola!%20Me%20interesa%20un%20producto de su página,%20quisiera%20tener%20mas%20información."},
    {"nombre": "Iphone 14 Pro Max 128GB", "detail": "", "categoria": "iphone", "precio": 1160, "pic": "../assets/img/iphone_14_pm_black.jpg", "text": "https://wa.me/1156634529?text=Hola!%20Me%20interesa%20un%20producto de su página,%20quisiera%20tener%20mas%20información."},
    {"nombre": "Iphone 14 Pro Max 256GB", "detail": "", "categoria": "iphone", "precio": 1260, "pic": "../assets/img/iphone_14_pm_black.jpg", "text": "https://wa.me/1156634529?text=Hola!%20Me%20interesa%20un%20producto de su página,%20quisiera%20tener%20mas%20información."},
    {"nombre": "Iphone 13 128GB", "detail": "", "categoria": "iphone", "precio": 730, "pic": "../assets/img/iphone_13_black.jpg", "text": "https://wa.me/1156634529?text=Hola!%20Me%20interesa%20un%20producto de su página,%20quisiera%20tener%20mas%20información."},
    {"nombre": "Iphone 11 64GB", "detail": "", "categoria": "iphone", "precio": 480, "pic": "../assets/img/iphone_11_black.jpg", "text": "https://wa.me/1156634529?text=Hola!%20Me%20interesa%20un%20producto de su página,%20quisiera%20tener%20mas%20información."},
    {"nombre": "Iphone XR 64GB", "detail": "", "categoria": "iphone", "precio": 390, "pic": "../assets/img/iphone_xr_black.jpg", "text": "https://wa.me/1156634529?text=Hola!%20Me%20interesa%20un%20producto de su página,%20quisiera%20tener%20mas%20información."},
    {"nombre": "PS5 Standard", "detail": "Sony PlayStation 5 Edición Estandar + GOW/COD + 1 Joystick", "categoria": "consola", "precio": 720, "pic": "../assets/img/ps5gow.jpg", "text": "https://wa.me/1156634529?text=Hola!%20Me%20interesa%20un%20producto de su página,%20quisiera%20tener%20mas%20información."},
    {"nombre": "Sony PS5 825GB Spiderman 2 Edition", "detail": "Play Station 5 Edición Spiderman + Spiderman 2 por encargue de 7 a 10 días hábiles. Abonas cuando recibís", "categoria": "consola", "precio": 1000, "pic": "../assets/img/ps5spiderman.jpg", "text": "https://wa.me/1156634529?text=Hola!%20Me%20interesa%20un%20producto de su página,%20quisiera%20tener%20mas%20información."},
    {"nombre": "Joystick PS5", "detail": "Joystick Inalámbrico Sony Playstation Dualsense Ps5 White", "categoria": "consola", "precio": 100, "pic": "../assets/img/joystick.jpg", "text": 3},
    {"nombre": "Nintendo Switch OLED 64GB", "detail": "Nintendo Switch OLED 64GB Standard White/Neón", "categoria": "consola", "precio": 385, "pic": "../assets/img/nintendo.jpg", "text": "https://wa.me/1156634529?text=Hola!%20Me%20interesa%20un%20producto de su página,%20quisiera%20tener%20mas%20información."},
    {"nombre": "Nintendo Switch OLED 64GB", "detail": "Nintendo Switch 64GB OLED - Splatoon 3 / Pokemon Scarlet & Violet Edition", "categoria": "consola", "precio": 420, "pic": "../assets/img/nintendopokemon.jpg", "text": "https://wa.me/1156634529?text=Hola!%20Me%20interesa%20un%20producto de su página,%20quisiera%20tener%20mas%20información."},
    {"nombre": "Xbox One Series X 1Tb", "detail": "Xbox One Series X 1Tb Black por encargue de 7 a 10 días hábiles. Abonas cuando recibís", "categoria": "consola", "precio": 726, "pic": "../assets/img/xboxx.jpg", "text": "https://wa.me/1156634529?text=Hola!%20Me%20interesa%20un%20producto de su página,%20quisiera%20tener%20mas%20información."},
    {"nombre": "Xbox One Series S 512GB Digital", "detail": "Xbox One Series S 512GB White Digital por encargue de 7 a 10 días hábiles. Abonas cuando recibís", "categoria": "consola", "precio": 426, "pic": "../assets/img/xboxs.jpg", "text": "https://wa.me/1156634529?text=Hola!%20Me%20interesa%20un%20producto de su página,%20quisiera%20tener%20mas%20información."}
]